json_context/__init__.py
json_context-0.0.2.dist-info/METADATA
json_context-0.0.2.dist-info/WHEEL
json_context-0.0.2.dist-info/top_level.txt
json_context-0.0.2.dist-info/RECORD
